runningstatistics/__init__.py
runningstatistics/statstracker.py
runningstatistics-0.0.1.dist-info/LICENSE
runningstatistics-0.0.1.dist-info/METADATA
runningstatistics-0.0.1.dist-info/WHEEL
runningstatistics-0.0.1.dist-info/top_level.txt
runningstatistics-0.0.1.dist-info/RECORD
