Metadata-Version: 2.1
Name: runningstatistics
Version: 0.0.1
Summary: A simple module for computing the sample statistics of an array in a running/online fashion.
Author-email: Jonathan Lindbloom <jonathan@lindbloom.com>
Project-URL: Homepage, https://github.com/jlindbloom/running-stats
Project-URL: Bug Tracker, https://github.com/jlindbloom/running-stats/issues
Keywords: statistics
Classifier: Programming Language :: Python :: 3
Classifier: License :: OSI Approved :: MIT License
Classifier: Operating System :: OS Independent
Classifier: Topic :: Scientific/Engineering :: Mathematics
Requires-Python: >=3.7
License-File: LICENSE
